{
    "call_center": {
        "arachne": 64.57565195033,
        "arachne_runtime": 12391.856052751747,
        "bq": 65.71968173980713,
        "bq_baseline_runtime": 29449.21700000001,
        "multi_cloud_plan": "aws",
        "percent_diff": 1.7407719562710224,
        "profiling_cost": 135.29945712371844,
        "profiling_runtime": 45939.66304227086
    },
    "catalog_page": {
        "arachne": 62.0753493309021,
        "arachne_runtime": 29104.663000000004,
        "bq": 62.0753493309021,
        "bq_baseline_runtime": 29104.663000000004,
        "multi_cloud_plan": "gcp",
        "percent_diff": 0.0,
        "profiling_cost": 131.5097363593044,
        "profiling_runtime": 45475.152939963016
    },
    "catalog_returns": {
        "arachne": 54.370646953582764,
        "arachne_runtime": 20833.994,
        "bq": 54.370646953582764,
        "bq_baseline_runtime": 20833.994,
        "multi_cloud_plan": "gcp",
        "percent_diff": 0.0,
        "profiling_cost": 119.62686076630418,
        "profiling_runtime": 35022.07200460514
    },
    "catalog_sales": {
        "arachne": 29.0746808052063,
        "arachne_runtime": 12311.433000000003,
        "bq": 29.0746808052063,
        "bq_baseline_runtime": 12311.433000000003,
        "multi_cloud_plan": "gcp",
        "percent_diff": 0.0,
        "profiling_cost": 74.32105167382825,
        "profiling_runtime": 21606.498340940376
    },
    "customer": {
        "arachne": 51.99275541305542,
        "arachne_runtime": 23349.041000000005,
        "bq": 51.99275541305542,
        "bq_baseline_runtime": 23349.041000000005,
        "multi_cloud_plan": "gcp",
        "percent_diff": 0.0,
        "profiling_cost": 116.42001331293676,
        "profiling_runtime": 35665.71913469423
    },
    "customer_address": {
        "arachne": 53.743770122528076,
        "arachne_runtime": 23769.817000000014,
        "bq": 53.743770122528076,
        "bq_baseline_runtime": 23769.817000000014,
        "multi_cloud_plan": "gcp",
        "percent_diff": 0.0,
        "profiling_cost": 120.69086911484044,
        "profiling_runtime": 38109.02557090831
    },
    "customer_demographics": {
        "arachne": 58.007469177246094,
        "arachne_runtime": 21214.16300000001,
        "bq": 58.007469177246094,
        "bq_baseline_runtime": 21214.16300000001,
        "multi_cloud_plan": "gcp",
        "percent_diff": 0.0,
        "profiling_cost": 125.54873240383667,
        "profiling_runtime": 36021.49977280882
    },
    "date_dim": {
        "arachne": 7.423117160797119,
        "arachne_runtime": 2806.467,
        "bq": 7.423117160797119,
        "bq_baseline_runtime": 2806.467,
        "multi_cloud_plan": "gcp",
        "percent_diff": 0.0,
        "profiling_cost": 65.00368703369642,
        "profiling_runtime": 9383.245532003053
    },
    "household_demographics": {
        "arachne": 59.121453285217285,
        "arachne_runtime": 21505.640000000007,
        "bq": 59.121453285217285,
        "bq_baseline_runtime": 21505.640000000007,
        "multi_cloud_plan": "gcp",
        "percent_diff": 0.0,
        "profiling_cost": 127.63504049233087,
        "profiling_runtime": 37115.19343576987
    },
    "income_band": {
        "arachne": 64.46245140758927,
        "arachne_runtime": 12298.327768549883,
        "bq": 64.6934266090393,
        "bq_baseline_runtime": 29432.815000000006,
        "multi_cloud_plan": "aws",
        "percent_diff": 0.35703040255679247,
        "profiling_cost": 134.1870832073918,
        "profiling_runtime": 45852.10797049995
    },
    "inventory": {
        "arachne": 63.66522617260607,
        "arachne_runtime": 12140.836991332566,
        "bq": 65.45267295837402,
        "bq_baseline_runtime": 23872.071000000014,
        "multi_cloud_plan": "aws",
        "percent_diff": 2.730899602686537,
        "profiling_cost": 133.84076412417448,
        "profiling_runtime": 39879.266048926875
    },
    "item": {
        "arachne": 24.602078437805176,
        "arachne_runtime": 11228.741999999997,
        "bq": 24.602078437805176,
        "bq_baseline_runtime": 11228.741999999997,
        "multi_cloud_plan": "gcp",
        "percent_diff": 0.0,
        "profiling_cost": 88.0950244882014,
        "profiling_runtime": 22693.594669565475
    },
    "promotion": {
        "arachne": 59.894278049468994,
        "arachne_runtime": 22579.33700000001,
        "bq": 59.894278049468994,
        "bq_baseline_runtime": 22579.33700000001,
        "multi_cloud_plan": "gcp",
        "percent_diff": 0.0,
        "profiling_cost": 128.4877653144,
        "profiling_runtime": 38254.908667848635
    },
    "reason": {
        "arachne": 64.40960836410522,
        "arachne_runtime": 29149.644,
        "bq": 64.40960836410522,
        "bq_baseline_runtime": 29149.644,
        "multi_cloud_plan": "gcp",
        "percent_diff": 0.0,
        "profiling_cost": 133.78129335705634,
        "profiling_runtime": 45468.162928412334
    },
    "ship_mode": {
        "arachne": 64.69609034688771,
        "arachne_runtime": 12491.362622892579,
        "bq": 66.03170824050903,
        "bq_baseline_runtime": 29704.262000000002,
        "multi_cloud_plan": "aws",
        "percent_diff": 2.02269171767685,
        "profiling_cost": 135.70317516094278,
        "profiling_runtime": 46270.46367518828
    },
    "store": {
        "arachne": 38.050840854644775,
        "arachne_runtime": 19434.616,
        "bq": 38.050840854644775,
        "bq_baseline_runtime": 19434.616,
        "multi_cloud_plan": "gcp",
        "percent_diff": 0.0,
        "profiling_cost": 103.80737733993811,
        "profiling_runtime": 32766.27341693043
    },
    "store_returns": {
        "arachne": 51.91222286224365,
        "arachne_runtime": 24971.00700000001,
        "bq": 51.91222286224365,
        "bq_baseline_runtime": 24971.00700000001,
        "multi_cloud_plan": "gcp",
        "percent_diff": 0.0,
        "profiling_cost": 116.1252223762579,
        "profiling_runtime": 39062.40409507767
    },
    "store_sales": {
        "arachne": 6.591599464416504,
        "arachne_runtime": 8720.065000000002,
        "bq": 6.591599464416504,
        "bq_baseline_runtime": 8720.065000000002,
        "multi_cloud_plan": "gcp",
        "percent_diff": 0.0,
        "profiling_cost": 41.701111965783596,
        "profiling_runtime": 13770.831041177325
    },
    "time_dim": {
        "arachne": 63.80164384841919,
        "arachne_runtime": 28742.780999999995,
        "bq": 63.80164384841919,
        "bq_baseline_runtime": 28742.780999999995,
        "multi_cloud_plan": "gcp",
        "percent_diff": 0.0,
        "profiling_cost": 133.31610398704464,
        "profiling_runtime": 45179.38058038853
    },
    "warehouse": {
        "arachne": 63.79253001651515,
        "arachne_runtime": 12275.803224479616,
        "bq": 64.82900047302246,
        "bq_baseline_runtime": 23665.578999999987,
        "multi_cloud_plan": "multi",
        "percent_diff": 1.5987759319822,
        "profiling_cost": 133.84856680399596,
        "profiling_runtime": 39693.174187717115
    },
    "web_page": {
        "arachne": 64.5737953856514,
        "arachne_runtime": 12390.328419182544,
        "bq": 64.7880449295044,
        "bq_baseline_runtime": 29591.18700000001,
        "multi_cloud_plan": "aws",
        "percent_diff": 0.3306930222792254,
        "profiling_cost": 134.3232300162275,
        "profiling_runtime": 46044.798382792236
    },
    "web_returns": {
        "arachne": 56.72325420379639,
        "arachne_runtime": 27105.24,
        "bq": 56.72325420379639,
        "bq_baseline_runtime": 27105.24,
        "multi_cloud_plan": "gcp",
        "percent_diff": 0.0,
        "profiling_cost": 123.53705414331402,
        "profiling_runtime": 41923.93132459257
    },
    "web_sales": {
        "arachne": 33.7215895652771,
        "arachne_runtime": 19348.598999999995,
        "bq": 33.7215895652771,
        "bq_baseline_runtime": 19348.598999999995,
        "multi_cloud_plan": "gcp",
        "percent_diff": 0.0,
        "profiling_cost": 87.7942191969162,
        "profiling_runtime": 29565.525529842893
    },
    "web_site": {
        "arachne": 61.557907581329346,
        "arachne_runtime": 28732.643,
        "bq": 61.557907581329346,
        "bq_baseline_runtime": 28732.643,
        "multi_cloud_plan": "gcp",
        "percent_diff": 0.0,
        "profiling_cost": 130.8644129323196,
        "profiling_runtime": 44997.3107496652
    }
}