{
    "call_center": {
        "moved_tables": [
            "catalog_page",
            "catalog_returns",
            "catalog_sales",
            "customer",
            "customer_address",
            "customer_demographics",
            "date_dim",
            "household_demographics",
            "income_band",
            "inventory",
            "item",
            "promotion",
            "reason",
            "ship_mode",
            "store",
            "store_returns",
            "store_sales",
            "time_dim",
            "warehouse",
            "web_page",
            "web_returns",
            "web_sales",
            "web_site"
        ],
        "optimal_cost": 54.67937781189838,
        "optimal_runtime": 39758.14408040559
    },
    "catalog_page": {
        "moved_tables": [
            "call_center",
            "catalog_returns",
            "catalog_sales",
            "customer",
            "customer_address",
            "customer_demographics",
            "date_dim",
            "household_demographics",
            "income_band",
            "inventory",
            "item",
            "promotion",
            "reason",
            "ship_mode",
            "store",
            "store_returns",
            "store_sales",
            "time_dim",
            "warehouse",
            "web_page",
            "web_returns",
            "web_sales",
            "web_site"
        ],
        "optimal_cost": 54.7395661956305,
        "optimal_runtime": 39956.292631686665
    },
    "catalog_returns": {
        "moved_tables": [
            "call_center",
            "catalog_sales",
            "customer",
            "customer_address",
            "customer_demographics",
            "date_dim",
            "household_demographics",
            "income_band",
            "inventory",
            "item",
            "promotion",
            "reason",
            "ship_mode",
            "store",
            "store_returns",
            "store_sales",
            "time_dim",
            "warehouse",
            "web_page",
            "web_returns",
            "web_sales",
            "web_site"
        ],
        "optimal_cost": 51.97966724252769,
        "optimal_runtime": 35566.06391161587
    },
    "catalog_sales": {
        "moved_tables": [
            "customer",
            "customer_address",
            "customer_demographics",
            "date_dim",
            "household_demographics",
            "item",
            "promotion",
            "reason",
            "store",
            "store_sales",
            "time_dim"
        ],
        "optimal_cost": 29.491164257457445,
        "optimal_runtime": 13313.446332641412
    },
    "customer": {
        "moved_tables": [],
        "optimal_cost": 49.628448486328125,
        "optimal_runtime": 9870.032000000001
    },
    "customer_address": {
        "moved_tables": [],
        "optimal_cost": 49.88613724708557,
        "optimal_runtime": 10181.380000000003
    },
    "customer_demographics": {
        "moved_tables": [
            "call_center",
            "catalog_page",
            "catalog_returns",
            "catalog_sales",
            "customer",
            "customer_address",
            "date_dim",
            "household_demographics",
            "inventory",
            "item",
            "promotion",
            "reason",
            "ship_mode",
            "store",
            "store_returns",
            "store_sales",
            "time_dim",
            "warehouse",
            "web_page",
            "web_returns",
            "web_sales",
            "web_site"
        ],
        "optimal_cost": 53.915219557973266,
        "optimal_runtime": 37254.37544066738
    },
    "date_dim": {
        "moved_tables": [],
        "optimal_cost": 4.604446887969971,
        "optimal_runtime": 536.8040000000001
    },
    "household_demographics": {
        "moved_tables": [
            "call_center",
            "catalog_page",
            "catalog_returns",
            "catalog_sales",
            "customer",
            "customer_address",
            "customer_demographics",
            "date_dim",
            "inventory",
            "item",
            "promotion",
            "reason",
            "ship_mode",
            "store",
            "store_returns",
            "store_sales",
            "time_dim",
            "warehouse",
            "web_page",
            "web_returns",
            "web_sales",
            "web_site"
        ],
        "optimal_cost": 54.23434003421054,
        "optimal_runtime": 38297.91277046269
    },
    "income_band": {
        "moved_tables": [
            "call_center",
            "catalog_page",
            "catalog_returns",
            "catalog_sales",
            "customer",
            "customer_address",
            "customer_demographics",
            "date_dim",
            "household_demographics",
            "inventory",
            "item",
            "promotion",
            "reason",
            "ship_mode",
            "store",
            "store_returns",
            "store_sales",
            "time_dim",
            "warehouse",
            "web_page",
            "web_returns",
            "web_sales",
            "web_site"
        ],
        "optimal_cost": 54.731088491162744,
        "optimal_runtime": 39927.814639396966
    },
    "inventory": {
        "moved_tables": [
            "call_center",
            "catalog_page",
            "catalog_returns",
            "catalog_sales",
            "customer",
            "customer_address",
            "customer_demographics",
            "date_dim",
            "household_demographics",
            "income_band",
            "item",
            "promotion",
            "reason",
            "ship_mode",
            "store",
            "store_returns",
            "store_sales",
            "time_dim",
            "warehouse",
            "web_page",
            "web_returns",
            "web_sales",
            "web_site"
        ],
        "optimal_cost": 53.927904780764415,
        "optimal_runtime": 39327.79002111917
    },
    "item": {
        "moved_tables": [],
        "optimal_cost": 32.549965381622314,
        "optimal_runtime": 3456.4110000000005
    },
    "promotion": {
        "moved_tables": [
            "call_center",
            "catalog_page",
            "catalog_returns",
            "catalog_sales",
            "customer",
            "customer_address",
            "customer_demographics",
            "date_dim",
            "household_demographics",
            "income_band",
            "inventory",
            "item",
            "reason",
            "ship_mode",
            "store",
            "store_returns",
            "store_sales",
            "time_dim",
            "warehouse",
            "web_page",
            "web_returns",
            "web_sales",
            "web_site"
        ],
        "optimal_cost": 54.257238977613,
        "optimal_runtime": 38373.03232554672
    },
    "reason": {
        "moved_tables": [
            "call_center",
            "catalog_page",
            "catalog_returns",
            "catalog_sales",
            "customer",
            "customer_address",
            "customer_demographics",
            "date_dim",
            "household_demographics",
            "income_band",
            "inventory",
            "item",
            "promotion",
            "ship_mode",
            "store",
            "store_returns",
            "store_sales",
            "time_dim",
            "warehouse",
            "web_page",
            "web_returns",
            "web_sales",
            "web_site"
        ],
        "optimal_cost": 54.78479957465157,
        "optimal_runtime": 40104.053595428355
    },
    "ship_mode": {
        "moved_tables": [
            "call_center",
            "catalog_page",
            "catalog_returns",
            "catalog_sales",
            "customer",
            "customer_address",
            "customer_demographics",
            "date_dim",
            "household_demographics",
            "income_band",
            "inventory",
            "item",
            "promotion",
            "reason",
            "store",
            "store_returns",
            "store_sales",
            "time_dim",
            "warehouse",
            "web_page",
            "web_returns",
            "web_sales",
            "web_site"
        ],
        "optimal_cost": 54.83639862545009,
        "optimal_runtime": 40273.36206621025
    },
    "store": {
        "moved_tables": [],
        "optimal_cost": 38.1888747215271,
        "optimal_runtime": 9607.33
    },
    "store_returns": {
        "moved_tables": [
            "customer",
            "customer_address",
            "customer_demographics",
            "date_dim",
            "household_demographics",
            "item",
            "promotion",
            "reason",
            "store",
            "store_sales",
            "time_dim"
        ],
        "optimal_cost": 47.9089875721242,
        "optimal_runtime": 13313.446332641412
    },
    "store_sales": {
        "moved_tables": [],
        "optimal_cost": 8.456605672836304,
        "optimal_runtime": 5352.938
    },
    "time_dim": {
        "moved_tables": [
            "call_center",
            "catalog_page",
            "catalog_returns",
            "catalog_sales",
            "customer",
            "customer_address",
            "customer_demographics",
            "date_dim",
            "household_demographics",
            "income_band",
            "inventory",
            "item",
            "promotion",
            "reason",
            "ship_mode",
            "store",
            "store_returns",
            "store_sales",
            "warehouse",
            "web_page",
            "web_returns",
            "web_sales",
            "web_site"
        ],
        "optimal_cost": 54.80938584022152,
        "optimal_runtime": 40185.159204816446
    },
    "warehouse": {
        "moved_tables": [
            "call_center",
            "catalog_page",
            "catalog_returns",
            "catalog_sales",
            "customer",
            "customer_address",
            "customer_demographics",
            "date_dim",
            "household_demographics",
            "income_band",
            "item",
            "promotion",
            "reason",
            "store",
            "store_returns",
            "store_sales",
            "time_dim",
            "web_page",
            "web_returns",
            "web_sales",
            "web_site"
        ],
        "optimal_cost": 54.21443385243607,
        "optimal_runtime": 38932.29630309995
    },
    "web_page": {
        "moved_tables": [
            "call_center",
            "catalog_page",
            "catalog_returns",
            "catalog_sales",
            "customer",
            "customer_address",
            "customer_demographics",
            "date_dim",
            "household_demographics",
            "income_band",
            "inventory",
            "item",
            "promotion",
            "reason",
            "ship_mode",
            "store",
            "store_returns",
            "store_sales",
            "time_dim",
            "warehouse",
            "web_returns",
            "web_sales",
            "web_site"
        ],
        "optimal_cost": 54.906284339050345,
        "optimal_runtime": 40502.69947228208
    },
    "web_returns": {
        "moved_tables": [
            "call_center",
            "catalog_returns",
            "catalog_sales",
            "customer",
            "customer_address",
            "customer_demographics",
            "date_dim",
            "household_demographics",
            "income_band",
            "inventory",
            "item",
            "promotion",
            "reason",
            "ship_mode",
            "store",
            "store_returns",
            "store_sales",
            "time_dim",
            "warehouse",
            "web_page",
            "web_sales",
            "web_site"
        ],
        "optimal_cost": 53.314354920921325,
        "optimal_runtime": 37544.769507613964
    },
    "web_sales": {
        "moved_tables": [
            "customer",
            "customer_address",
            "customer_demographics",
            "date_dim",
            "household_demographics",
            "item",
            "promotion",
            "reason",
            "store",
            "store_sales",
            "time_dim"
        ],
        "optimal_cost": 36.03046732180376,
        "optimal_runtime": 13313.446332641412
    },
    "web_site": {
        "moved_tables": [
            "call_center",
            "catalog_returns",
            "catalog_sales",
            "customer",
            "customer_address",
            "customer_demographics",
            "date_dim",
            "household_demographics",
            "income_band",
            "inventory",
            "item",
            "promotion",
            "reason",
            "ship_mode",
            "store",
            "store_returns",
            "store_sales",
            "time_dim",
            "warehouse",
            "web_page",
            "web_returns",
            "web_sales"
        ],
        "optimal_cost": 54.65598443632544,
        "optimal_runtime": 39682.07894536713
    }
}